{
  "name": "scala-cli",
  "argv": [
    "C:\\Users\\Ivan\\AppData\\Local\\Coursier\\data\\bin\\.scala-cli.aux.exe",
    "bsp",
    "--json-options",
    "C:\\Users\\Ivan\\Documents\\GitHub\\AutoDocumentation\\.scala-build\\ide-options-v2.json",
    "--json-launcher-options",
    "C:\\Users\\Ivan\\Documents\\GitHub\\AutoDocumentation\\.scala-build\\ide-launcher-options.json",
    "--envs-file",
    "C:\\Users\\Ivan\\Documents\\GitHub\\AutoDocumentation\\.scala-build\\ide-envs.json",
    "C:\\Users\\Ivan\\Documents\\GitHub\\AutoDocumentation"
  ],
  "version": "1.6.1",
  "bspVersion": "2.1.1",
  "languages": [
    "scala",
    "java"
  ]
}